b64uuid/__init__.py
b64uuid/__main__.py
b64uuid/b64uuid.py
b64uuid/version.py
b64uuid-0.1.dist-info/AUTHORS.md
b64uuid-0.1.dist-info/LICENSE.txt
b64uuid-0.1.dist-info/METADATA
b64uuid-0.1.dist-info/WHEEL
b64uuid-0.1.dist-info/entry_points.txt
b64uuid-0.1.dist-info/top_level.txt
b64uuid-0.1.dist-info/RECORD
