Metadata-Version: 2.1
Name: b64uuid
Version: 0.1
Summary: A small library and tool to encode/decode a python UUID object to/from a 22 characters shorter URL safe base64 string.
Home-page: https://github.com/tanbro/b64uuid
Author: liu xue yan
Author-email: liu_xue_yan@foxmail.com
License: AGPLv3+
Keywords: uuid base64 shortid urlsafe urlsafe-base64
Platform: UNKNOWN
Classifier: Development Status :: 4 - Beta
Classifier: License :: OSI Approved :: GNU Affero General Public License v3 or later (AGPLv3+)
Classifier: Programming Language :: Python :: 3
Classifier: Topic :: Utilities
Classifier: Topic :: Software Development :: Libraries :: Python Modules
Requires-Python: >=3.5
